{
    "channel": "fun_fun_function",
    "channel_id": "UCO1cgjhGzsSYb1rsB4bFe4Q",
    "data": [
        {
            "id": "RMtq0RCLuzs",
            "title": "More GraphQL - Fun Fun Function",
            "href": "https://www.youtube.com/watch?v=RMtq0RCLuzs",
            "duration": " - Duration: 20 minutes.",
            "views": "1,455 views",
            "active": true,
            "watched": false
        },
        {
            "id": "lAJWHHUz8_8",
            "title": "GraphQL Basics - Fun Fun Function",
            "href": "https://www.youtube.com/watch?v=lAJWHHUz8_8",
            "duration": " - Duration: 48 minutes.",
            "views": "2,553 views",
            "active": true,
            "watched": false
        },
        {
            "id": "6YBV1cKRqzU",
            "title": "Advanced Dependency Injection without classes - Fun Fun Function",
            "href": "https://www.youtube.com/watch?v=6YBV1cKRqzU",
            "duration": " - Duration: 28 minutes.",
            "views": "1,564 views",
            "active": true,
            "watched": false
        },
        {
            "id": "sD94szvFqGw",
            "title": "Dependency Injection without classes - Fun Fun Function",
            "href": "https://www.youtube.com/watch?v=sD94szvFqGw",
            "duration": " - Duration: 22 minutes.",
            "views": "12,887 views",
            "active": true,
            "watched": false
        },
        {
            "id": "VGB9HbL1GHk",
            "title": "Let's code with function composition - Fun Fun Function",
            "href": "https://www.youtube.com/watch?v=VGB9HbL1GHk",
            "duration": " - Duration: 1 hour, 46 minutes.",
            "views": "18,884 views",
            "active": true,
            "watched": false
        },
        {
            "id": "f8IgdnYIwOU",
            "title": "Error handling Promises in JavaScript - Fun Fun Function",
            "href": "https://www.youtube.com/watch?v=f8IgdnYIwOU",
            "duration": " - Duration: 10 minutes.",
            "views": "14,641 views",
            "active": true,
            "watched": false
        },
        {
            "id": "trP9q703x0o",
            "title": "Patreon + Fun Fun Forum launch",
            "href": "https://www.youtube.com/watch?v=trP9q703x0o",
            "duration": " - Duration: 9 minutes, 55 seconds.",
            "views": "11,557 views",
            "active": true,
            "watched": false
        },
        {
            "id": "568g8hxJJp4",
            "title": "async / await in JavaScript - What, Why and How - Fun Fun Function",
            "href": "https://www.youtube.com/watch?v=568g8hxJJp4",
            "duration": " - Duration: 24 minutes.",
            "views": "30,995 views",
            "active": true,
            "watched": false
        },
        {
            "id": "kMfTQvMaghQ",
            "title": "Backend/Frontend apartheid - Q&A P3 - Fun Fun Function",
            "href": "https://www.youtube.com/watch?v=kMfTQvMaghQ",
            "duration": " - Duration: 3 minutes, 43 seconds.",
            "views": "13,518 views",
            "active": true,
            "watched": false
        },
        {
            "id": "aA4be5LbbEA",
            "title": "How I manage my back pain as a programmer - Q&A P4 - Fun Fun Function",
            "href": "https://www.youtube.com/watch?v=aA4be5LbbEA",
            "duration": " - Duration: 2 minutes, 38 seconds.",
            "views": "9,819 views",
            "active": true,
            "watched": false
        },
        {
            "id": "cyDC8q-f6IE",
            "title": "Becoming a game developer? - Q&A P1 - Fun Fun Function",
            "href": "https://www.youtube.com/watch?v=cyDC8q-f6IE",
            "duration": " - Duration: 3 minutes, 18 seconds.",
            "views": "8,414 views",
            "active": true,
            "watched": false
        },
        {
            "id": "A52aiKWRZD8",
            "title": "Where should unit tests run? -  Q&A P2 - Fun Fun Function",
            "href": "https://www.youtube.com/watch?v=A52aiKWRZD8",
            "duration": " - Duration: 3 minutes, 31 seconds.",
            "views": "6,836 views",
            "active": true,
            "watched": false
        },
        {
            "id": "N0_JyynMRog",
            "title": "My opinion on TypeScript - Q&A P5 - Fun Fun Function",
            "href": "https://www.youtube.com/watch?v=N0_JyynMRog",
            "duration": " - Duration: 91 seconds.",
            "views": "12,712 views",
            "active": true,
            "watched": false
        },
        {
            "id": "gDzEu4CY4Gk",
            "title": "Vacation re-run: What editor do you use",
            "href": "https://www.youtube.com/watch?v=gDzEu4CY4Gk",
            "duration": " - Duration: 70 seconds.",
            "views": "9,610 views",
            "active": true,
            "watched": false
        },
        {
            "id": "AcRmoLJXqig",
            "title": "Must watch Fun Fun Function episodes P1 (Vacation re-runs)",
            "href": "https://www.youtube.com/watch?v=AcRmoLJXqig",
            "duration": " - Duration: 4 minutes, 20 seconds.",
            "views": "9,107 views",
            "active": true,
            "watched": false
        },
        {
            "id": "7VxBn_ZgOek",
            "title": "Getting started with CircleCI - Continuous Integration P2 - Fun Fun Function",
            "href": "https://www.youtube.com/watch?v=7VxBn_ZgOek",
            "duration": " - Duration: 24 minutes.",
            "views": "19,489 views",
            "active": true,
            "watched": false
        },
        {
            "id": "dYQIkV2L-eg",
            "title": "ESNext Pipeline Operator - Fun Fun Function",
            "href": "https://www.youtube.com/watch?v=dYQIkV2L-eg",
            "duration": " - Duration: 20 minutes.",
            "views": "22,085 views",
            "active": true,
            "watched": false
        },
        {
            "id": "ymPOI4gWQFY",
            "title": "Continuous Integration - What's the point? - Continuous Integration P1 - Fun Fun Function",
            "href": "https://www.youtube.com/watch?v=ymPOI4gWQFY",
            "duration": " - Duration: 15 minutes.",
            "views": "39,409 views",
            "active": true,
            "watched": false
        },
        {
            "id": "K-wHkzGAiK0",
            "title": "I've made a horrible mistake - MPJ's Musings - Fun Fun Function",
            "href": "https://www.youtube.com/watch?v=K-wHkzGAiK0",
            "duration": " - Duration: 14 minutes.",
            "views": "22,860 views",
            "active": true,
            "watched": false
        },
        {
            "id": "k2gidnJyGZA",
            "title": "Time to leave your job? - MPJ's Musings - Fun Fun Function",
            "href": "https://www.youtube.com/watch?v=k2gidnJyGZA",
            "duration": " - Duration: 11 minutes.",
            "views": "24,217 views",
            "active": true,
            "watched": false
        },
        {
            "id": "hNA0WLQ0jcw",
            "title": "Burnout due to value conflict - MPJ's Musings - Fun Fun Function",
            "href": "https://www.youtube.com/watch?v=hNA0WLQ0jcw",
            "duration": " - Duration: 6 minutes, 10 seconds.",
            "views": "16,827 views",
            "active": true,
            "watched": false
        },
        {
            "id": "4_SvuUYQ5Fo",
            "title": "UML, Cucumber and modeling reality - MPJ's Musings - Fun Fun Function",
            "href": "https://www.youtube.com/watch?v=4_SvuUYQ5Fo",
            "duration": " - Duration: 12 minutes.",
            "views": "16,755 views",
            "active": true,
            "watched": false
        },
        {
            "id": "Tllw4EPhLiQ",
            "title": "Class keyword - Object Creation in JavaScript P7 - Fun Fun Function",
            "href": "https://www.youtube.com/watch?v=Tllw4EPhLiQ",
            "duration": " - Duration: 17 minutes.",
            "views": "24,575 views",
            "active": true,
            "watched": false
        },
        {
            "id": "RleN-6uMF04",
            "title": "Top 8 developer habits: Teaching - Fun Fun Function",
            "href": "https://www.youtube.com/watch?v=RleN-6uMF04",
            "duration": " - Duration: 16 minutes.",
            "views": "16,525 views",
            "active": true,
            "watched": false
        },
        {
            "id": "mZNXkQxu9Rw",
            "title": "Top 8 developer habits: Getting shit done - Fun Fun Function",
            "href": "https://www.youtube.com/watch?v=mZNXkQxu9Rw",
            "duration": " - Duration: 31 minutes.",
            "views": "36,903 views",
            "active": true,
            "watched": false
        },
        {
            "id": "DwQ7psiU23I",
            "title": "Top 8 developer habits: Perseverance - Fun Fun Function",
            "href": "https://www.youtube.com/watch?v=DwQ7psiU23I",
            "duration": " - Duration: 22 minutes.",
            "views": "25,048 views",
            "active": true,
            "watched": false
        },
        {
            "id": "EmGfdlixQHo",
            "title": "Templating languages: The hidden costs - Fun Fun Function",
            "href": "https://www.youtube.com/watch?v=EmGfdlixQHo",
            "duration": " - Duration: 28 minutes.",
            "views": "25,133 views",
            "active": true,
            "watched": false
        },
        {
            "id": "fOf838UlTPU",
            "title": "Whiteboard interviews and other questions - Fun Fun Function",
            "href": "https://www.youtube.com/watch?v=fOf838UlTPU",
            "duration": " - Duration: 25 minutes.",
            "views": "17,471 views",
            "active": true,
            "watched": false
        },
        {
            "id": "9-8E8L_77-8",
            "title": "Standard Deviation - Data Science in JavaScript - Fun Fun Function",
            "href": "https://www.youtube.com/watch?v=9-8E8L_77-8",
            "duration": " - Duration: 31 minutes.",
            "views": "19,837 views",
            "active": true,
            "watched": false
        },
        {
            "id": "9R_XUMoLHeU",
            "title": "How to deal with bad bosses + other questions - Fun Fun Function",
            "href": "https://www.youtube.com/watch?v=9R_XUMoLHeU",
            "duration": " - Duration: 18 minutes.",
            "views": "18,059 views",
            "active": true,
            "watched": false
        },
        {
            "id": "M6_a2wBK-yc",
            "title": "How software dies - MPJ's Musings - Fun Fun Function",
            "href": "https://www.youtube.com/watch?v=M6_a2wBK-yc",
            "duration": " - Duration: 17 minutes.",
            "views": "18,349 views",
            "active": true,
            "watched": false
        },
        {
            "id": "yGh0bjzj4IQ",
            "title": "Declarative programming - Fun Fun Function",
            "href": "https://www.youtube.com/watch?v=yGh0bjzj4IQ",
            "duration": " - Duration: 14 minutes.",
            "views": "27,767 views",
            "active": true,
            "watched": false
        },
        {
            "id": "FSbImq-uzFk",
            "title": "Coding and Cooking - MPJ's Musings - Fun Fun Function",
            "href": "https://www.youtube.com/watch?v=FSbImq-uzFk",
            "duration": " - Duration: 11 minutes.",
            "views": "14,539 views",
            "active": true,
            "watched": false
        }
    ]
}