{
    "channel": "nycxclothes",
    "channel_id": "UCDhzksj3HUGds3zf7DqhHjA",
    "data": [
        {
            "id": "Lzr4UrCF6GQ",
            "title": "Travel Vlog: Austin, Texas",
            "href": "https://www.youtube.com/watch?v=Lzr4UrCF6GQ",
            "duration": " - Duration: 4 minutes, 35 seconds.",
            "views": "412 views",
            "active": true,
            "watched": false
        },
        {
            "id": "jWkZQpsfKZs",
            "title": "Top 5 Coffee Shops in NYC || Part I",
            "href": "https://www.youtube.com/watch?v=jWkZQpsfKZs",
            "duration": " - Duration: 2 minutes, 57 seconds.",
            "views": "407 views",
            "active": true,
            "watched": false
        },
        {
            "id": "RTMktCr0nKw",
            "title": "Travel Vlog: Washington, DC",
            "href": "https://www.youtube.com/watch?v=RTMktCr0nKw",
            "duration": " - Duration: 7 minutes.",
            "views": "325 views",
            "active": true,
            "watched": false
        },
        {
            "id": "cJfEnPEka_g",
            "title": "What To Wear to Work || Office Wear Lookbook",
            "href": "https://www.youtube.com/watch?v=cJfEnPEka_g",
            "duration": " - Duration: 2 minutes, 33 seconds.",
            "views": "511 views",
            "active": true,
            "watched": false
        },
        {
            "id": "BvbYGd426z0",
            "title": "A Day In our Life || New York Fashion Week + Brunch + Party! ♡",
            "href": "https://www.youtube.com/watch?v=BvbYGd426z0",
            "duration": " - Duration: 3 minutes, 19 seconds.",
            "views": "278 views",
            "active": true,
            "watched": false
        },
        {
            "id": "e4bIGCIKMMg",
            "title": "Valentine's Day Outfit Ideas ♡",
            "href": "https://www.youtube.com/watch?v=e4bIGCIKMMg",
            "duration": " - Duration: 2 minutes, 16 seconds.",
            "views": "290 views",
            "active": true,
            "watched": false
        },
        {
            "id": "fowfdcxqaQY",
            "title": "Church Outfit Ideas: Winter 2017",
            "href": "https://www.youtube.com/watch?v=fowfdcxqaQY",
            "duration": " - Duration: 119 seconds.",
            "views": "477 views",
            "active": true,
            "watched": false
        },
        {
            "id": "0gJEEHV41PU",
            "title": "Travel Vlog: Portland, Maine",
            "href": "https://www.youtube.com/watch?v=0gJEEHV41PU",
            "duration": " - Duration: 4 minutes, 57 seconds.",
            "views": "2,117 views",
            "active": true,
            "watched": false
        },
        {
            "id": "rEtVWHSerbM",
            "title": "Winter Lookbook 2017",
            "href": "https://www.youtube.com/watch?v=rEtVWHSerbM",
            "duration": " - Duration: 4 minutes, 54 seconds.",
            "views": "276 views",
            "active": true,
            "watched": false
        },
        {
            "id": "yb634dH4X-8",
            "title": "How to Survive Finals Week: Fashion Edition",
            "href": "https://www.youtube.com/watch?v=yb634dH4X-8",
            "duration": " - Duration: 3 minutes, 33 seconds.",
            "views": "258 views",
            "active": true,
            "watched": false
        },
        {
            "id": "lCiR5KLpYks",
            "title": "Outfits of the week: Fall 2016 Edition",
            "href": "https://www.youtube.com/watch?v=lCiR5KLpYks",
            "duration": " - Duration: 116 seconds.",
            "views": "174 views",
            "active": true,
            "watched": false
        },
        {
            "id": "5z41T1maLHs",
            "title": "2. Strangers",
            "href": "https://www.youtube.com/watch?v=5z41T1maLHs",
            "duration": " - Duration: 115 seconds.",
            "views": "142 views",
            "active": true,
            "watched": false
        },
        {
            "id": "d5nUqHtSy3c",
            "title": "NYC Guide: Top 3 Coffee Shops in Brooklyn",
            "href": "https://www.youtube.com/watch?v=d5nUqHtSy3c",
            "duration": " - Duration: 3 minutes, 24 seconds.",
            "views": "1,215 views",
            "active": true,
            "watched": false
        },
        {
            "id": "qScuX8zlAFU",
            "title": "Summer to Fall Transition Outfits 2016",
            "href": "https://www.youtube.com/watch?v=qScuX8zlAFU",
            "duration": " - Duration: 4 minutes, 31 seconds.",
            "views": "360 views",
            "active": true,
            "watched": false
        },
        {
            "id": "I9jDIxdkWZM",
            "title": "Summer Lookbook 2016",
            "href": "https://www.youtube.com/watch?v=I9jDIxdkWZM",
            "duration": " - Duration: 4 minutes, 59 seconds.",
            "views": "517 views",
            "active": true,
            "watched": false
        },
        {
            "id": "ZWGrg0V1dIg",
            "title": "How to spend 24 hours in NYC : NYCxClothes Takesmeth3re",
            "href": "https://www.youtube.com/watch?v=ZWGrg0V1dIg",
            "duration": " - Duration: 3 minutes, 45 seconds.",
            "views": "171 views",
            "active": true,
            "watched": false
        },
        {
            "id": "3R6UkFxXgX0",
            "title": "Guide to New York City Eats: Brunch with Creatives",
            "href": "https://www.youtube.com/watch?v=3R6UkFxXgX0",
            "duration": " - Duration: 6 minutes, 32 seconds.",
            "views": "265 views",
            "active": true,
            "watched": false
        },
        {
            "id": "VR18sL-XrfY",
            "title": "1. NYC Snapshots",
            "href": "https://www.youtube.com/watch?v=VR18sL-XrfY",
            "duration": " - Duration: 100 seconds.",
            "views": "250 views",
            "active": true,
            "watched": false
        },
        {
            "id": "Aipf2NvodnA",
            "title": "Music Festival Looks: Coachella, Lollapalooza, Governor's Ball",
            "href": "https://www.youtube.com/watch?v=Aipf2NvodnA",
            "duration": " - Duration: 4 minutes, 23 seconds.",
            "views": "410 views",
            "active": true,
            "watched": false
        },
        {
            "id": "Vi9CVaHYBCg",
            "title": "Outfits of the Week : Spring 2016",
            "href": "https://www.youtube.com/watch?v=Vi9CVaHYBCg",
            "duration": " - Duration: 4 minutes, 14 seconds.",
            "views": "439 views",
            "active": true,
            "watched": false
        },
        {
            "id": "uaHKvuOsr7k",
            "title": "Guide to New York City Eats: Brunch with Creatives",
            "href": "https://www.youtube.com/watch?v=uaHKvuOsr7k",
            "duration": " - Duration: 4 minutes, 37 seconds.",
            "views": "383 views",
            "active": true,
            "watched": false
        },
        {
            "id": "Cj4kSnZMF3Q",
            "title": "What To Wear: Spring 2016 Lookbook",
            "href": "https://www.youtube.com/watch?v=Cj4kSnZMF3Q",
            "duration": " - Duration: 3 minutes, 12 seconds.",
            "views": "1,574 views",
            "active": true,
            "watched": false
        },
        {
            "id": "W65PNrLjYK0",
            "title": "10 Annoying People on Snapchat",
            "href": "https://www.youtube.com/watch?v=W65PNrLjYK0",
            "duration": " - Duration: 4 minutes, 7 seconds.",
            "views": "537 views",
            "active": true,
            "watched": false
        },
        {
            "id": "XoRSa0Fdr7s",
            "title": "What To Wear: Valentine's Day 2016",
            "href": "https://www.youtube.com/watch?v=XoRSa0Fdr7s",
            "duration": " - Duration: 3 minutes, 48 seconds.",
            "views": "385 views",
            "active": true,
            "watched": false
        },
        {
            "id": "hk_1jMTW_ec",
            "title": "Travel Vlog: New Orleans, Louisiana",
            "href": "https://www.youtube.com/watch?v=hk_1jMTW_ec",
            "duration": " - Duration: 6 minutes, 26 seconds.",
            "views": "1,434 views",
            "active": true,
            "watched": false
        },
        {
            "id": "aBCV7yIIKjg",
            "title": "Holiday Party Outfits 2015",
            "href": "https://www.youtube.com/watch?v=aBCV7yIIKjg",
            "duration": " - Duration: 4 minutes, 5 seconds.",
            "views": "315 views",
            "active": true,
            "watched": false
        },
        {
            "id": "BbL-riEGLtY",
            "title": "A day in my life // nycxclothes",
            "href": "https://www.youtube.com/watch?v=BbL-riEGLtY",
            "duration": " - Duration: 3 minutes, 9 seconds.",
            "views": "356 views",
            "active": true,
            "watched": false
        },
        {
            "id": "F4DehskMopI",
            "title": "Fall Try-On Haul: Zara, H&M, J. Crew & More!",
            "href": "https://www.youtube.com/watch?v=F4DehskMopI",
            "duration": " - Duration: 4 minutes, 6 seconds.",
            "views": "421 views",
            "active": true,
            "watched": false
        },
        {
            "id": "4E7-9a8YtFs",
            "title": "Fall Lookbook 2015 + GIVEAWAY (Closed) !! ♡",
            "href": "https://www.youtube.com/watch?v=4E7-9a8YtFs",
            "duration": " - Duration: 6 minutes, 20 seconds.",
            "views": "836 views",
            "active": true,
            "watched": false
        },
        {
            "id": "rp-crcWLZZA",
            "title": "Interview Outfit Ideas",
            "href": "https://www.youtube.com/watch?v=rp-crcWLZZA",
            "duration": " - Duration: 5 minutes, 2 seconds.",
            "views": "474 views",
            "active": true,
            "watched": false
        },
        {
            "id": "YhuEgwMBGJU",
            "title": "Back to school Outfit Ideas 2015",
            "href": "https://www.youtube.com/watch?v=YhuEgwMBGJU",
            "duration": " - Duration: 4 minutes, 3 seconds.",
            "views": "524 views",
            "active": true,
            "watched": false
        },
        {
            "id": "f2SO68tQK3w",
            "title": "Real Talk: Back to School Advice",
            "href": "https://www.youtube.com/watch?v=f2SO68tQK3w",
            "duration": " - Duration: 8 minutes, 9 seconds.",
            "views": "325 views",
            "active": true,
            "watched": false
        },
        {
            "id": "Dve3TLpDL-0",
            "title": "Things to do when you're bored",
            "href": "https://www.youtube.com/watch?v=Dve3TLpDL-0",
            "duration": " - Duration: 5 minutes, 27 seconds.",
            "views": "315 views",
            "active": true,
            "watched": false
        },
        {
            "id": "tO_p1XyVaO4",
            "title": "Outfits of the week: July 2015",
            "href": "https://www.youtube.com/watch?v=tO_p1XyVaO4",
            "duration": " - Duration: 2 minutes, 21 seconds.",
            "views": "253 views",
            "active": true,
            "watched": false
        },
        {
            "id": "rpoig84kuIE",
            "title": "Summer Lookbook: Philadelphia Edition",
            "href": "https://www.youtube.com/watch?v=rpoig84kuIE",
            "duration": " - Duration: 4 minutes, 24 seconds.",
            "views": "352 views",
            "active": true,
            "watched": false
        },
        {
            "id": "CDS0o-Ujbdk",
            "title": "Spring to Summer Looks 2015 // nycxclothes",
            "href": "https://www.youtube.com/watch?v=CDS0o-Ujbdk",
            "duration": " - Duration: 3 minutes, 30 seconds.",
            "views": "311 views",
            "active": true,
            "watched": false
        },
        {
            "id": "ePkkxnmaYXE",
            "title": "Church outfit ideas",
            "href": "https://www.youtube.com/watch?v=ePkkxnmaYXE",
            "duration": " - Duration: 3 minutes, 43 seconds.",
            "views": "6,556 views",
            "active": true,
            "watched": false
        },
        {
            "id": "KErFhfNyXwA",
            "title": "Music festival looks: Coachella, Governor's ball, Lollapalooza etc...",
            "href": "https://www.youtube.com/watch?v=KErFhfNyXwA",
            "duration": " - Duration: 2 minutes, 10 seconds.",
            "views": "339 views",
            "active": true,
            "watched": false
        },
        {
            "id": "1bfGqhrNo5k",
            "title": "Huge Spring Try-on Haul: H&M, Zara, TopShop etc. + GIVEAWAY !! ♡♡",
            "href": "https://www.youtube.com/watch?v=1bfGqhrNo5k",
            "duration": " - Duration: 4 minutes, 19 seconds.",
            "views": "306 views",
            "active": true,
            "watched": false
        },
        {
            "id": "_kPr0r2LyOo",
            "title": "Outfits of the Week: March 2015",
            "href": "https://www.youtube.com/watch?v=_kPr0r2LyOo",
            "duration": " - Duration: 3 minutes, 5 seconds.",
            "views": "524 views",
            "active": true,
            "watched": false
        },
        {
            "id": "DQ1IT-fCSAY",
            "title": "New York Fashion Week 2015",
            "href": "https://www.youtube.com/watch?v=DQ1IT-fCSAY",
            "duration": " - Duration: 3 minutes, 48 seconds.",
            "views": "244 views",
            "active": true,
            "watched": false
        },
        {
            "id": "NC02TTy661I",
            "title": "Collective Winter Haul : Zara, Forever 21, H&M & more + GIVEAWAY !!! (CLOSED)",
            "href": "https://www.youtube.com/watch?v=NC02TTy661I",
            "duration": " - Duration: 3 minutes, 55 seconds.",
            "views": "772 views",
            "active": true,
            "watched": false
        },
        {
            "id": "vLvHnKhEzA4",
            "title": "Last minute DIY Holiday Gifts",
            "href": "https://www.youtube.com/watch?v=vLvHnKhEzA4",
            "duration": " - Duration: 4 minutes, 31 seconds.",
            "views": "347 views",
            "active": true,
            "watched": false
        },
        {
            "id": "y3t81o9jEw0",
            "title": "Sister Tag // nycxclothes",
            "href": "https://www.youtube.com/watch?v=y3t81o9jEw0",
            "duration": " - Duration: 7 minutes, 37 seconds.",
            "views": "576 views",
            "active": true,
            "watched": false
        },
        {
            "id": "dPbtcKy3ERw",
            "title": "Fall Lookbook 2014",
            "href": "https://www.youtube.com/watch?v=dPbtcKy3ERw",
            "duration": " - Duration: 4 minutes, 7 seconds.",
            "views": "635 views",
            "active": true,
            "watched": false
        },
        {
            "id": "Y9UWRxCqgRw",
            "title": "Fall Essentials 2014",
            "href": "https://www.youtube.com/watch?v=Y9UWRxCqgRw",
            "duration": " - Duration: 2 minutes, 33 seconds.",
            "views": "544 views",
            "active": true,
            "watched": false
        },
        {
            "id": "Idtm1EwE4wM",
            "title": "Outfits of the week : October 2014",
            "href": "https://www.youtube.com/watch?v=Idtm1EwE4wM",
            "duration": " - Duration: 102 seconds.",
            "views": "590 views",
            "active": true,
            "watched": false
        },
        {
            "id": "gL1hFIq0USM",
            "title": "Fall Lookbook 2014 : Part one",
            "href": "https://www.youtube.com/watch?v=gL1hFIq0USM",
            "duration": " - Duration: 3 minutes, 33 seconds.",
            "views": "1,280 views",
            "active": true,
            "watched": false
        },
        {
            "id": "PJrxkfNBEKw",
            "title": "New York Fashion Week 2014",
            "href": "https://www.youtube.com/watch?v=PJrxkfNBEKw",
            "duration": " - Duration: 4 minutes, 18 seconds.",
            "views": "577 views",
            "active": true,
            "watched": false
        },
        {
            "id": "9dEUd9fOKsg",
            "title": "Back to school outfit ideas",
            "href": "https://www.youtube.com/watch?v=9dEUd9fOKsg",
            "duration": " - Duration: 4 minutes, 10 seconds.",
            "views": "895 views",
            "active": true,
            "watched": false
        }
    ]
}